{
  "employee": [{
  "id": 1,
  "first_name": "Sydelle",
  "last_name": "Gerbi",
  "email": "sgerbi0@cocolog-nifty.com",
  "gender": "Male",
  "position": 3
}, {
  "id": 2,
  "first_name": "Boycey",
  "last_name": "Mohun",
  "email": "bmohun1@sphinn.com",
  "gender": "Female",
  "position": 7
}, {
  "id": 3,
  "first_name": "Marjorie",
  "last_name": "Queen",
  "email": "mqueen2@state.gov",
  "gender": "Female",
  "position": 10
}, {
  "id": 4,
  "first_name": "Kati",
  "last_name": "McFaul",
  "email": "kmcfaul3@rambler.ru",
  "gender": "Female",
  "position": 1
}, {
  "id": 5,
  "first_name": "Nani",
  "last_name": "Rockell",
  "email": "nrockell4@nature.com",
  "gender": "Female",
  "position": 4
}, {
  "id": 6,
  "first_name": "Lucian",
  "last_name": "Drayson",
  "email": "ldrayson5@mail.ru",
  "gender": "Male",
  "position": 10
}, {
  "id": 7,
  "first_name": "Arlyn",
  "last_name": "McCourt",
  "email": "amccourt6@networkadvertising.org",
  "gender": "Male",
  "position": 7
}, {
  "id": 8,
  "first_name": "Harman",
  "last_name": "Scoterbosh",
  "email": "hscoterbosh7@last.fm",
  "gender": "Male",
  "position": 1
}, {
  "id": 9,
  "first_name": "Patrice",
  "last_name": "Bielfeld",
  "email": "pbielfeld8@ning.com",
  "gender": "Female",
  "position": 5
}, {
  "id": 10,
  "first_name": "Marleah",
  "last_name": "Ingleson",
  "email": "mingleson9@google.cn",
  "gender": "Male",
  "position": 3
}, {
  "id": 11,
  "first_name": "Devlin",
  "last_name": "Bazley",
  "email": "dbazleya@google.fr",
  "gender": "Female",
  "position": 6
}, {
  "id": 12,
  "first_name": "Kingsley",
  "last_name": "Dall",
  "email": "kdallb@netlog.com",
  "gender": "Male",
  "position": 9
}, {
  "id": 13,
  "first_name": "Robby",
  "last_name": "Digan",
  "email": "rdiganc@mtv.com",
  "gender": "Agender",
  "position": 8
}, {
  "id": 14,
  "first_name": "Issiah",
  "last_name": "Orneblow",
  "email": "iorneblowd@mapy.cz",
  "gender": "Male",
  "position": 9
}, {
  "id": 15,
  "first_name": "Franni",
  "last_name": "Piscopello",
  "email": "fpiscopelloe@amazon.co.jp",
  "gender": "Female",
  "position": 1
}, {
  "id": 16,
  "first_name": "Ines",
  "last_name": "Jesper",
  "email": "ijesperf@google.com.hk",
  "gender": "Female",
  "position": 5
}, {
  "id": 17,
  "first_name": "Peta",
  "last_name": "Ody",
  "email": "podyg@ow.ly",
  "gender": "Male",
  "position": 3
}, {
  "id": 18,
  "first_name": "Raviv",
  "last_name": "Cawker",
  "email": "rcawkerh@microsoft.com",
  "gender": "Female",
  "position": 7
}, {
  "id": 19,
  "first_name": "Giavani",
  "last_name": "Core",
  "email": "gcorei@independent.co.uk",
  "gender": "Male",
  "position": 8
}, {
  "id": 20,
  "first_name": "Edmund",
  "last_name": "Blackater",
  "email": "eblackaterj@seesaa.net",
  "gender": "Male",
  "position": 9
}, {
  "id": 21,
  "first_name": "Wit",
  "last_name": "Studdard",
  "email": "wstuddardk@zdnet.com",
  "gender": "Male",
  "position": 1
}, {
  "id": 22,
  "first_name": "Hercules",
  "last_name": "Hadny",
  "email": "hhadnyl@huffingtonpost.com",
  "gender": "Male",
  "position": 4
}, {
  "id": 23,
  "first_name": "Randi",
  "last_name": "Dives",
  "email": "rdivesm@disqus.com",
  "gender": "Male",
  "position": 1
}, {
  "id": 24,
  "first_name": "Jillene",
  "last_name": "Sogg",
  "email": "jsoggn@issuu.com",
  "gender": "Male",
  "position": 6
}, {
  "id": 25,
  "first_name": "Claire",
  "last_name": "Jurczik",
  "email": "cjurcziko@buzzfeed.com",
  "gender": "Male",
  "position": 1
}, {
  "id": 26,
  "first_name": "Chryste",
  "last_name": "Gerbl",
  "email": "cgerblp@imageshack.us",
  "gender": "Male",
  "position": 3
}, {
  "id": 27,
  "first_name": "Hamlen",
  "last_name": "Kidney",
  "email": "hkidneyq@ucoz.com",
  "gender": "Female",
  "position": 1
}, {
  "id": 28,
  "first_name": "Kalli",
  "last_name": "Osban",
  "email": "kosbanr@ebay.com",
  "gender": "Female",
  "position": 2
}, {
  "id": 29,
  "first_name": "Ardath",
  "last_name": "Tolson",
  "email": "atolsons@yale.edu",
  "gender": "Female",
  "position": 2
}, {
  "id": 30,
  "first_name": "Francene",
  "last_name": "Dugald",
  "email": "fdugaldt@theguardian.com",
  "gender": "Female",
  "position": 9
}, {
  "id": 31,
  "first_name": "Frederico",
  "last_name": "Lanceley",
  "email": "flanceleyu@surveymonkey.com",
  "gender": "Genderqueer",
  "position": 9
}, {
  "id": 32,
  "first_name": "Trixi",
  "last_name": "Mueller",
  "email": "tmuellerv@edublogs.org",
  "gender": "Male",
  "position": 8
}, {
  "id": 33,
  "first_name": "Sal",
  "last_name": "Kowalski",
  "email": "skowalskiw@aboutads.info",
  "gender": "Male",
  "position": 7
}, {
  "id": 34,
  "first_name": "Hollyanne",
  "last_name": "Brimacombe",
  "email": "hbrimacombex@google.com",
  "gender": "Female",
  "position": 2
}, {
  "id": 35,
  "first_name": "Jackson",
  "last_name": "Cansdill",
  "email": "jcansdilly@whitehouse.gov",
  "gender": "Female",
  "position": 8
}, {
  "id": 36,
  "first_name": "Kelcy",
  "last_name": "Pilling",
  "email": "kpillingz@wikimedia.org",
  "gender": "Female",
  "position": 6
}, {
  "id": 37,
  "first_name": "Heloise",
  "last_name": "Francom",
  "email": "hfrancom10@comcast.net",
  "gender": "Female",
  "position": 7
}, {
  "id": 38,
  "first_name": "Rossie",
  "last_name": "Brosio",
  "email": "rbrosio11@constantcontact.com",
  "gender": "Male",
  "position": 5
}, {
  "id": 39,
  "first_name": "Farleigh",
  "last_name": "Pymer",
  "email": "fpymer12@deviantart.com",
  "gender": "Male",
  "position": 2
}, {
  "id": 40,
  "first_name": "Brittney",
  "last_name": "Rendall",
  "email": "brendall13@auda.org.au",
  "gender": "Female",
  "position": 4
}, {
  "id": 41,
  "first_name": "Nana",
  "last_name": "Lemm",
  "email": "nlemm14@yelp.com",
  "gender": "Female",
  "position": 5
}, {
  "id": 42,
  "first_name": "Bebe",
  "last_name": "Roark",
  "email": "broark15@walmart.com",
  "gender": "Male",
  "position": 8
}, {
  "id": 43,
  "first_name": "Marya",
  "last_name": "Gladden",
  "email": "mgladden16@hugedomains.com",
  "gender": "Male",
  "position": 1
}, {
  "id": 44,
  "first_name": "Alexei",
  "last_name": "Stansbie",
  "email": "astansbie17@opera.com",
  "gender": "Male",
  "position": 6
}, {
  "id": 45,
  "first_name": "Jerrilyn",
  "last_name": "Scotchmer",
  "email": "jscotchmer18@amazon.com",
  "gender": "Female",
  "position": 4
}, {
  "id": 46,
  "first_name": "Mirabelle",
  "last_name": "Parman",
  "email": "mparman19@meetup.com",
  "gender": "Female",
  "position": 5
}, {
  "id": 47,
  "first_name": "Sylvia",
  "last_name": "Beecham",
  "email": "sbeecham1a@independent.co.uk",
  "gender": "Female",
  "position": 1
}, {
  "id": 48,
  "first_name": "Antonino",
  "last_name": "Stannislawski",
  "email": "astannislawski1b@alibaba.com",
  "gender": "Female",
  "position": 7
}, {
  "id": 49,
  "first_name": "Car",
  "last_name": "Bourtoumieux",
  "email": "cbourtoumieux1c@google.cn",
  "gender": "Female",
  "position": 5
}, {
  "id": 50,
  "first_name": "Wit",
  "last_name": "Hackin",
  "email": "whackin1d@cnet.com",
  "gender": "Male",
  "position": 10
}],
	"positions": [{
  "position": 1,
  "name": "Support specialist"
}, {
  "position": 2,
  "name": "Computer programmer"
}, {
  "position": 3,
  "name": "Quality assurance tester"
}, {
  "position": 4,
  "name": "Web developer"
}, {
  "position": 5,
  "name": "Systems analyst"
}, {
  "position": 6,
  "name": "Network engineer"
}, {
  "position": 7,
  "name": "Database administrator"
}, {
  "position": 8,
  "name": "IT security specialist"
}, {
  "position": 9,
  "name": "Business analyst"
}, {
  "position": 10,
  "name": "DevOps engineer"
}]

}
